{
  "generator-jhipster": {
    "applicationType": "monolith",
    "gitCompany": "",
    "baseName": "SampleApplication",
    "packageName": "com.cihankamilogut.testapp",
    "packageFolder": "com/cihankamilogut/testapp",
    "serverPort": 8080,
    "serviceDiscoveryType": "eureka",
    "authenticationType": "jwt",
    "cacheProvider": "ehcache",
    "enableHibernateCache": true,
    "websocket": "spring-websocket",
    "databaseType": "sql",
    "devDatabaseType": "h2Disk",
    "prodDatabaseType": "postgresql",
    "searchEngine": "elasticsearch",
    "enableSwaggerCodegen": "true",
    "messageBroker": "kafka",
    "buildTool": "maven",
    "useSass": true,
    "clientPackageManager": "npm",
    "testFrameworks": ["cucumber"],
    "enableTranslation": true,
    "nativeLanguage": "en",
    "languages": ["en", "tr"],
    "clientFramework": "react",
    "jhiPrefix": "jhi",
    "withAdminUi": true,
    "jhipsterVersion": "7.3.0",
    "skipClient": false,
    "skipServer": false,
    "skipUserManagement": false,
    "skipCheckLengthOfIdentifier": false,
    "skipFakeData": false,
    "entitySuffix": "",
    "dtoSuffix": "DTO",
    "blueprints": [],
    "otherModules": [],
    "pages": [],
    "creationTimestamp": 1634460230060,
    "jwtSecretKey": "MmQxMzdjMzg0MDMxZTU2Y2UzNmU2ZWYwZGRiZmUxMWNmMjA5M2NkM2FlNjc0MGM4OTgzZDdkNWNjZjliY2NhZDBjYmM0ODZhN2QwM2UzMzQ3YTMxNGU5M2U3ZTUxNDViNGJiZjhmNjM0MDZiMjhhM2I0ZDA1ODQ2ZThlZDhkNDE=",
    "devServerPort": 9060,
    "clientTheme": "none",
    "clientThemeVariant": "",
    "reactive": false,
    "enableGradleEnterprise": false
  },
  "git-provider": "GitHub",
  "git-company": "chnkmlogt",
  "repository-name": "sample-application"
}
